collective.volto.blocksfield-2.2.0-py3.10-nspkg.pth
collective/volto/blocksfield/__init__.py
collective/volto/blocksfield/configure.zcml
collective/volto/blocksfield/field.py
collective/volto/blocksfield/indexers.py
collective/volto/blocksfield/interfaces.py
collective/volto/blocksfield/permissions.zcml
collective/volto/blocksfield/setuphandlers.py
collective/volto/blocksfield/testing.py
collective/volto/blocksfield/adapters/__init__.py
collective/volto/blocksfield/adapters/configure.zcml
collective/volto/blocksfield/adapters/searchabletext_indexers.py
collective/volto/blocksfield/events/__init__.py
collective/volto/blocksfield/events/configure.zcml
collective/volto/blocksfield/events/handler.py
collective/volto/blocksfield/locales/README.rst
collective/volto/blocksfield/locales/__init__.py
collective/volto/blocksfield/locales/collective.volto.blocksfield.pot
collective/volto/blocksfield/locales/update.py
collective/volto/blocksfield/locales/update.sh
collective/volto/blocksfield/locales/en/LC_MESSAGES/collective.volto.blocksfield.mo
collective/volto/blocksfield/locales/en/LC_MESSAGES/collective.volto.blocksfield.po
collective/volto/blocksfield/profiles/default/metadata.xml
collective/volto/blocksfield/profiles/uninstall/.gitkeep
collective/volto/blocksfield/restapi/__init__.py
collective/volto/blocksfield/restapi/configure.zcml
collective/volto/blocksfield/restapi/deserializers/__init__.py
collective/volto/blocksfield/restapi/deserializers/blocks.py
collective/volto/blocksfield/restapi/deserializers/configure.zcml
collective/volto/blocksfield/restapi/deserializers/dxfields.py
collective/volto/blocksfield/restapi/serializers/__init__.py
collective/volto/blocksfield/restapi/serializers/blocks.py
collective/volto/blocksfield/restapi/serializers/configure.zcml
collective/volto/blocksfield/restapi/serializers/dxfields.py
collective/volto/blocksfield/restapi/types/__init__.py
collective/volto/blocksfield/restapi/types/adapters.py
collective.volto.blocksfield-2.2.0.dist-info/LICENSE.GPL
collective.volto.blocksfield-2.2.0.dist-info/LICENSE.rst
collective.volto.blocksfield-2.2.0.dist-info/METADATA
collective.volto.blocksfield-2.2.0.dist-info/WHEEL
collective.volto.blocksfield-2.2.0.dist-info/entry_points.txt
collective.volto.blocksfield-2.2.0.dist-info/namespace_packages.txt
collective.volto.blocksfield-2.2.0.dist-info/top_level.txt
collective.volto.blocksfield-2.2.0.dist-info/RECORD
